{
  "summary": {
    "n_jobs": 32,
    "backend": "loky",
    "inner_n_jobs": 1,
    "total_train_wall_sec": 69.40077921100237,
    "best_seed": 0,
    "best_acc": 1.0,
    "best_params": {
      "mlpclassifier__alpha": 0.0001,
      "mlpclassifier__hidden_layer_sizes": [
        256
      ],
      "mlpclassifier__learning_rate_init": 0.001
    }
  },
  "per_seed": [
    {
      "seed": 0,
      "acc": 1.0,
      "best_params": {
        "mlpclassifier__alpha": 0.0001,
        "mlpclassifier__hidden_layer_sizes": [
          256
        ],
        "mlpclassifier__learning_rate_init": 0.001
      },
      "fit_time_gs_sec": 68.19706092200067,
      "fit_time_total_seed_sec": 68.20980072200109
    },
    {
      "seed": 1,
      "acc": 1.0,
      "best_params": {
        "mlpclassifier__alpha": 0.0001,
        "mlpclassifier__hidden_layer_sizes": [
          256
        ],
        "mlpclassifier__learning_rate_init": 0.001
      },
      "fit_time_gs_sec": 68.24475215500206,
      "fit_time_total_seed_sec": 68.25727816500148
    },
    {
      "seed": 2,
      "acc": 1.0,
      "best_params": {
        "mlpclassifier__alpha": 0.0001,
        "mlpclassifier__hidden_layer_sizes": [
          256
        ],
        "mlpclassifier__learning_rate_init": 0.001
      },
      "fit_time_gs_sec": 67.98962593800024,
      "fit_time_total_seed_sec": 68.00331987800018
    },
    {
      "seed": 3,
      "acc": 1.0,
      "best_params": {
        "mlpclassifier__alpha": 0.0001,
        "mlpclassifier__hidden_layer_sizes": [
          256
        ],
        "mlpclassifier__learning_rate_init": 0.001
      },
      "fit_time_gs_sec": 68.29986909700165,
      "fit_time_total_seed_sec": 68.31323924699973
    },
    {
      "seed": 4,
      "acc": 1.0,
      "best_params": {
        "mlpclassifier__alpha": 0.0001,
        "mlpclassifier__hidden_layer_sizes": [
          256
        ],
        "mlpclassifier__learning_rate_init": 0.001
      },
      "fit_time_gs_sec": 67.9424666499981,
      "fit_time_total_seed_sec": 67.95639495199794
    },
    {
      "seed": 5,
      "acc": 1.0,
      "best_params": {
        "mlpclassifier__alpha": 0.0001,
        "mlpclassifier__hidden_layer_sizes": [
          256
        ],
        "mlpclassifier__learning_rate_init": 0.001
      },
      "fit_time_gs_sec": 67.81615379399955,
      "fit_time_total_seed_sec": 67.8298862949996
    },
    {
      "seed": 6,
      "acc": 1.0,
      "best_params": {
        "mlpclassifier__alpha": 0.0001,
        "mlpclassifier__hidden_layer_sizes": [
          256
        ],
        "mlpclassifier__learning_rate_init": 0.001
      },
      "fit_time_gs_sec": 67.55404647699834,
      "fit_time_total_seed_sec": 67.5679112680009
    },
    {
      "seed": 7,
      "acc": 1.0,
      "best_params": {
        "mlpclassifier__alpha": 0.0001,
        "mlpclassifier__hidden_layer_sizes": [
          256
        ],
        "mlpclassifier__learning_rate_init": 0.001
      },
      "fit_time_gs_sec": 68.03575719999935,
      "fit_time_total_seed_sec": 68.04894439899726
    },
    {
      "seed": 8,
      "acc": 1.0,
      "best_params": {
        "mlpclassifier__alpha": 0.0001,
        "mlpclassifier__hidden_layer_sizes": [
          256
        ],
        "mlpclassifier__learning_rate_init": 0.001
      },
      "fit_time_gs_sec": 67.96070037699974,
      "fit_time_total_seed_sec": 67.97842700199908
    },
    {
      "seed": 9,
      "acc": 1.0,
      "best_params": {
        "mlpclassifier__alpha": 0.0001,
        "mlpclassifier__hidden_layer_sizes": [
          256
        ],
        "mlpclassifier__learning_rate_init": 0.001
      },
      "fit_time_gs_sec": 68.27149762000045,
      "fit_time_total_seed_sec": 68.2835650670022
    },
    {
      "seed": 10,
      "acc": 1.0,
      "best_params": {
        "mlpclassifier__alpha": 0.0001,
        "mlpclassifier__hidden_layer_sizes": [
          256
        ],
        "mlpclassifier__learning_rate_init": 0.001
      },
      "fit_time_gs_sec": 67.959706474001,
      "fit_time_total_seed_sec": 67.97362797999813
    },
    {
      "seed": 11,
      "acc": 1.0,
      "best_params": {
        "mlpclassifier__alpha": 0.0001,
        "mlpclassifier__hidden_layer_sizes": [
          256
        ],
        "mlpclassifier__learning_rate_init": 0.001
      },
      "fit_time_gs_sec": 68.32659928999783,
      "fit_time_total_seed_sec": 68.33859203300017
    },
    {
      "seed": 12,
      "acc": 1.0,
      "best_params": {
        "mlpclassifier__alpha": 0.0001,
        "mlpclassifier__hidden_layer_sizes": [
          256
        ],
        "mlpclassifier__learning_rate_init": 0.001
      },
      "fit_time_gs_sec": 68.05544724699939,
      "fit_time_total_seed_sec": 68.07324076700024
    },
    {
      "seed": 13,
      "acc": 1.0,
      "best_params": {
        "mlpclassifier__alpha": 0.0001,
        "mlpclassifier__hidden_layer_sizes": [
          256
        ],
        "mlpclassifier__learning_rate_init": 0.001
      },
      "fit_time_gs_sec": 67.81488881800033,
      "fit_time_total_seed_sec": 67.8285964880015
    },
    {
      "seed": 14,
      "acc": 1.0,
      "best_params": {
        "mlpclassifier__alpha": 0.0001,
        "mlpclassifier__hidden_layer_sizes": [
          256
        ],
        "mlpclassifier__learning_rate_init": 0.001
      },
      "fit_time_gs_sec": 68.10862344899942,
      "fit_time_total_seed_sec": 68.12109217200123
    },
    {
      "seed": 15,
      "acc": 1.0,
      "best_params": {
        "mlpclassifier__alpha": 0.0001,
        "mlpclassifier__hidden_layer_sizes": [
          256
        ],
        "mlpclassifier__learning_rate_init": 0.001
      },
      "fit_time_gs_sec": 68.36287209100192,
      "fit_time_total_seed_sec": 68.37466139699973
    }
  ]
}